argupdate/__init__.py
argupdate/argupdate.py
argupdate-0.0.1.dist-info/LICENSE.txt
argupdate-0.0.1.dist-info/METADATA
argupdate-0.0.1.dist-info/WHEEL
argupdate-0.0.1.dist-info/top_level.txt
argupdate-0.0.1.dist-info/RECORD
