Metadata-Version: 2.1
Name: argupdate
Version: 0.0.1
Summary: Update the value of args and kwargs destined for a callable.
Home-page: https://github.com/dmwyatt/argupdate
Author: Dustin Wyatt
Author-email: dustin.wyatt@gmail.com
License: UNKNOWN
Platform: UNKNOWN
Classifier: Programming Language :: Python :: 3.7
Classifier: License :: OSI Approved :: MIT License
Classifier: Operating System :: OS Independent
Requires-Python: ~=3.5
